monadcontainers/__init__.py
monadcontainers/monads.py
monadcontainers-0.2.0.dist-info/METADATA
monadcontainers-0.2.0.dist-info/WHEEL
monadcontainers-0.2.0.dist-info/licenses/LICENSE
monadcontainers-0.2.0.dist-info/RECORD
