Metadata-Version: 2.1
Name: monadcontainers
Version: 0.2.0
Summary: Python monads for functional programing
License-File: LICENSE
Requires-Python: >=3.8
